<?xml version="1.0" encoding="utf-8"?>
<!DOCTYPE markables SYSTEM "markables.dtd">
<markables xmlns="www.eml.org/NameSpaces/checks">
<markable mmax_level="checks" id="markable_0" span="word_10" check="NE:LOC" />
<markable mmax_level="checks" id="markable_1" span="word_12" check="NE:LOC" />
<markable mmax_level="checks" id="markable_2" span="word_19" check="NE:LOC" />
<markable mmax_level="checks" id="markable_3" span="word_46" check="NE:LOC" />
<markable mmax_level="checks" id="markable_4" span="word_51" check="NE:LOC" />
<markable mmax_level="checks" id="markable_5" span="word_66..word_67" check="NE:LOC" />
<markable mmax_level="checks" id="markable_6" span="word_72" check="NE:LOC" />
<markable mmax_level="checks" id="markable_7" span="word_73..word_75" check="NE:PER" />
<markable mmax_level="checks" id="markable_8" span="word_80" check="NE:PER" />
<markable mmax_level="checks" id="markable_9" span="word_99..word_100" check="NE:PER" />
<markable mmax_level="checks" id="markable_10" span="word_106..word_112" check="NE:ORG" />
<markable mmax_level="checks" id="markable_11" span="word_131" check="NE:PER" />
<markable mmax_level="checks" id="markable_12" span="word_138" check="NE:LOC" />
<markable mmax_level="checks" id="markable_13" span="word_152" check="NE:LOC" />
<markable mmax_level="checks" id="markable_14" span="word_178" check="NE:LOC" />
<markable mmax_level="checks" id="markable_15" span="word_189..word_190" check="NE:LOC" />
<markable mmax_level="checks" id="markable_16" span="word_216" check="NE:LOC" />
<markable mmax_level="checks" id="markable_17" span="word_244..word_245" check="NE:PER" />
<markable mmax_level="checks" id="markable_18" span="word_259..word_260" check="NE:LOC" />
<markable mmax_level="checks" id="markable_19" span="word_275..word_276" check="NE:LOC" />
<markable mmax_level="checks" id="markable_20" span="word_282" check="NE:LOC" />
<markable mmax_level="checks" id="markable_21" span="word_286..word_287" check="NE:LOC" />
<markable mmax_level="checks" id="markable_22" span="word_289" check="NE:LOC" />
<markable mmax_level="checks" id="markable_23" span="word_291" check="NE:LOC" />
<markable mmax_level="checks" id="markable_24" span="word_308" check="NE:PER" />
<markable mmax_level="checks" id="markable_25" span="word_318" check="NE:LOC" />
<markable mmax_level="checks" id="markable_26" span="word_319" check="NE:PER" />
<markable mmax_level="checks" id="markable_27" span="word_321" check="NE:PER" />
<markable mmax_level="checks" id="markable_28" span="word_325" check="NE:LOC" />
<markable mmax_level="checks" id="markable_29" span="word_347" check="NE:LOC" />
<markable mmax_level="checks" id="markable_30" span="word_422" check="NE:PER" />
<markable mmax_level="checks" id="markable_31" span="word_472" check="NE:PER" />
<markable mmax_level="checks" id="markable_32" span="word_478" check="NE:MISC" />
<markable mmax_level="checks" id="markable_33" span="word_524" check="NE:LOC" />
<markable mmax_level="checks" id="markable_34" span="word_538" check="NE:LOC" />
<markable mmax_level="checks" id="markable_35" span="word_559" check="NE:PER" />
<markable mmax_level="checks" id="markable_36" span="word_582..word_583" check="NE:LOC" />
<markable mmax_level="checks" id="markable_37" span="word_585" check="NE:LOC" />
<markable mmax_level="checks" id="markable_38" span="word_592..word_593" check="NE:ORG" />
<markable mmax_level="checks" id="markable_39" span="word_600..word_601" check="NE:MISC" />
<markable mmax_level="checks" id="markable_40" span="word_648" check="NE:LOC" />
<markable mmax_level="checks" id="markable_41" span="word_650" check="NE:PER" />
<markable mmax_level="checks" id="markable_42" span="word_683..word_684" check="NE:LOC" />
<markable mmax_level="checks" id="markable_43" span="word_686..word_687" check="NE:LOC" />
<markable mmax_level="checks" id="markable_44" span="word_736..word_737" check="NE:PER" />
<markable mmax_level="checks" id="markable_45" span="word_751" check="NE:LOC" />
<markable mmax_level="checks" id="markable_46" span="word_758..word_759" check="NE:LOC" />
<markable mmax_level="checks" id="markable_47" span="word_765" check="NE:LOC" />
<markable mmax_level="checks" id="markable_48" span="word_793..word_794" check="NE:PER" />
<markable mmax_level="checks" id="markable_49" span="word_798..word_800" check="NE:ORG" />
<markable mmax_level="checks" id="markable_50" span="word_802" check="NE:LOC" />
<markable mmax_level="checks" id="markable_51" span="word_832" check="NE:PER" />
</markables>
