<?xml version="1.0" encoding="utf-8"?>
<!DOCTYPE markables SYSTEM "markables.dtd">
<markables xmlns="www.eml.org/NameSpaces/checks">
<markable id="markable_285" span="word_118" mmax_level="checks"  check="antecedent-not-first" />
<markable id="markable_1331" span="word_545" mmax_level="checks"  check="chain-without-antecedent" />
<markable id="markable_3761" span="word_1590" mmax_level="checks"  check="antecedent-not-first" />
<markable id="markable_11302" span="word_4517" mmax_level="checks"  check="antecedent-not-first" />
<markable id="markable_1075" span="word_433" mmax_level="checks"  check="antecedent-not-first" />
<markable id="markable_11156" span="word_113" mmax_level="checks"  check="antecedent-not-first" />
<markable id="markable_11161" span="word_529" mmax_level="checks"  check="chain-without-antecedent" />
<markable id="markable_11160" span="word_467" mmax_level="checks"  check="chain-without-antecedent" />
<markable id="markable_11209" span="word_1627" mmax_level="checks"  check="antecedent-not-first" />
<markable id="markable_11290" span="word_4656" mmax_level="checks"  check="antecedent-not-first" />
<markable id="markable_1021" span="word_428" mmax_level="checks"  check="antecedent-not-first" />
<markable id="markable_11346" span="word_2856" mmax_level="checks"  check="antecedent-not-first" />
<markable id="markable_1277" span="word_534" mmax_level="checks"  check="chain-without-antecedent" />
<markable id="markable_11197" span="word_1232" mmax_level="checks"  check="antecedent-not-first" />
<markable id="markable_11195" span="word_1068" mmax_level="checks"  check="antecedent-not-first" />
<markable id="markable_11199" span="word_1269" mmax_level="checks"  check="antecedent-not-first" />
<markable id="markable_5488" span="word_2328" mmax_level="checks"  check="antecedent-not-first" />
<markable id="markable_5485" span="word_2315" mmax_level="checks"  check="antecedent-not-first" />
<markable id="markable_5522" span="word_2348" mmax_level="checks"  check="antecedent-not-first" />
<markable id="markable_11361" span="word_4523" mmax_level="checks"  check="antecedent-not-first" />
</markables>