<?xml version="1.0" encoding="UTF-8" ?>
<!DOCTYPE markables SYSTEM "markables.dtd">
<markables xmlns="www.eml.org/NameSpaces/sentence">
<markable mmax_level="sentence" orderid="0" id="markable_0" span="word_1..word_12" />
<markable mmax_level="sentence" orderid="1" id="markable_1" span="word_13..word_28" />
<markable mmax_level="sentence" orderid="2" id="markable_2" span="word_29..word_51" />
<markable mmax_level="sentence" orderid="3" id="markable_3" span="word_52..word_69" />
<markable mmax_level="sentence" orderid="4" id="markable_4" span="word_70..word_77" />
<markable mmax_level="sentence" orderid="5" id="markable_5" span="word_78..word_105" />
<markable mmax_level="sentence" orderid="6" id="markable_6" span="word_106..word_124" />
<markable mmax_level="sentence" orderid="7" id="markable_7" span="word_125..word_134" />
<markable mmax_level="sentence" orderid="8" id="markable_8" span="word_135..word_154" />
<markable mmax_level="sentence" orderid="9" id="markable_9" span="word_155..word_180" />
<markable mmax_level="sentence" orderid="10" id="markable_10" span="word_181..word_191" />
<markable mmax_level="sentence" orderid="11" id="markable_11" span="word_192..word_200" />
<markable mmax_level="sentence" orderid="12" id="markable_12" span="word_201..word_215" />
<markable mmax_level="sentence" orderid="13" id="markable_13" span="word_216..word_232" />
<markable mmax_level="sentence" orderid="14" id="markable_14" span="word_233..word_262" />
<markable mmax_level="sentence" orderid="15" id="markable_15" span="word_263..word_273" />
<markable mmax_level="sentence" orderid="16" id="markable_16" span="word_274..word_288" />
<markable mmax_level="sentence" orderid="17" id="markable_17" span="word_289..word_305" />
<markable mmax_level="sentence" orderid="18" id="markable_18" span="word_306..word_327" />
<markable mmax_level="sentence" orderid="19" id="markable_19" span="word_328..word_364" />
<markable mmax_level="sentence" orderid="20" id="markable_20" span="word_365..word_384" />
<markable mmax_level="sentence" orderid="21" id="markable_21" span="word_385..word_411" />
<markable mmax_level="sentence" orderid="22" id="markable_22" span="word_412..word_422" />
<markable mmax_level="sentence" orderid="23" id="markable_23" span="word_423..word_447" />
<markable mmax_level="sentence" orderid="24" id="markable_24" span="word_448..word_458" />
<markable mmax_level="sentence" orderid="25" id="markable_25" span="word_459..word_473" />
<markable mmax_level="sentence" orderid="26" id="markable_26" span="word_474..word_484" />
<markable mmax_level="sentence" orderid="27" id="markable_27" span="word_485..word_519" />
<markable mmax_level="sentence" orderid="28" id="markable_28" span="word_520..word_537" />
<markable mmax_level="sentence" orderid="29" id="markable_29" span="word_538..word_557" />
<markable mmax_level="sentence" orderid="30" id="markable_30" span="word_558..word_569" />
<markable mmax_level="sentence" orderid="31" id="markable_31" span="word_570..word_602" />
</markables>
